arquea/__init__.py
arquea/__main__.py
arquea/arquea.py
arquea/checksum.py
arquea/data.py
arquea/error.py
arquea/files.py
arquea/info.py
arquea/tools.py
arquea-0.2.2.dist-info/LICENSE
arquea-0.2.2.dist-info/METADATA
arquea-0.2.2.dist-info/WHEEL
arquea-0.2.2.dist-info/top_level.txt
arquea-0.2.2.dist-info/RECORD
