Metadata-Version: 2.1
Name: arquea
Version: 0.2.2
Summary: Um pequeno banco de dados NoSQL feito em Python.
Home-page: https://gabriellasaro.github.io/arqueadb/
Author: Gabriel Lasaro
Author-email: gabriellasarosaleze@gmail.com
License: UNKNOWN
Platform: UNKNOWN
Classifier: Programming Language :: Python :: 3
Classifier: License :: OSI Approved :: MIT License
Classifier: Operating System :: OS Independent
